setup.cfg
setup.py
slamon_agent/__init__.py
slamon_agent/agent.py
slamon_agent/communication.py
slamon_agent/executor.py
slamon_agent/timeutil.py
slamon_agent.egg-info/PKG-INFO
slamon_agent.egg-info/SOURCES.txt
slamon_agent.egg-info/dependency_links.txt
slamon_agent.egg-info/entry_points.txt
slamon_agent.egg-info/requires.txt
slamon_agent.egg-info/top_level.txt
slamon_agent/handlers/__init__.py
slamon_agent/handlers/task_handler.py
slamon_agent/handlers/url_http_status_task_handler.py
slamon_agent/handlers/wait_task_handler.py